<?xml version="1.0" encoding="utf-8"?>
<SoundBanksInfo Platform="Windows" BasePlatform="Windows" SchemaVersion="12" SoundbankVersion="135">
	<RootPaths>
		<ProjectRoot>T:\BUILDAGENT\WORK\9A7A8DD8B2E0B6C8\GAME\ASSETS\EXPORTED\AUDIO\</ProjectRoot>
		<SourceFilesRoot>T:\BUILDAGENT\WORK\9A7A8DD8B2E0B6C8\GAME\ASSETS\EXPORTED\AUDIO\.cache\Windows\</SourceFilesRoot>
		<SoundBanksRoot>T:\BUILDAGENT\WORK\9A7A8DD8B2E0B6C8\GAME\ASSETS\GAMEDATA\Audio\Windows\</SoundBanksRoot>
		<ExternalSourcesInputFile></ExternalSourcesInputFile>
		<ExternalSourcesOutputRoot>T:\BUILDAGENT\WORK\9A7A8DD8B2E0B6C8\GAME\ASSETS\EXPORTED\AUDIO\GeneratedSoundBanks\Windows</ExternalSourcesOutputRoot>
	</RootPaths>
	<SoundBanks>
		<SoundBank Id="3916867612" Language="SFX">
			<ObjectPath>\SoundBanks\PulseInstruments\PulseInstrument_PL_Drone_01_Index_18</ObjectPath>
			<ShortName>PulseInstrument_PL_Drone_01_Index_18</ShortName>
			<Path>PulseInstrument_PL_Drone_01_Index_18.bnk</Path>
			<IncludedEvents>
				<Event Id="2190106001" Name="Play_PL_Drone_01_Index_18_nms2017_mids_52" ObjectPath="\Events\PulseInstruments\PulseInstrument_PL_Drone_01_Index_18\Play_PL_Drone_01_Index_18_nms2017_mids_52">
					<ReferencedStreamedFiles>
						<File Id="24448990" Language="SFX">
							<ShortName>PulseInstruments\PL_Drone_01_Index_18\nms2017_mids_27.wav</ShortName>
							<Path>SFX\PulseInstruments\PL_Drone_01_Index_18\nms2017_mids_27_358B4EC2.wem</Path>
						</File>
						<File Id="33338840" Language="SFX">
							<ShortName>PulseInstruments\PL_Drone_01_Index_18\nms2017_mids_43.wav</ShortName>
							<Path>SFX\PulseInstruments\PL_Drone_01_Index_18\nms2017_mids_43_358B4EC2.wem</Path>
						</File>
						<File Id="35123807" Language="SFX">
							<ShortName>PulseInstruments\PL_Drone_01_Index_18\nms2017_mids_50.wav</ShortName>
							<Path>SFX\PulseInstruments\PL_Drone_01_Index_18\nms2017_mids_50_358B4EC2.wem</Path>
						</File>
						<File Id="37033565" Language="SFX">
							<ShortName>PulseInstruments\PL_Drone_01_Index_18\nms2017_mids_51.wav</ShortName>
							<Path>SFX\PulseInstruments\PL_Drone_01_Index_18\nms2017_mids_51_358B4EC2.wem</Path>
						</File>
						<File Id="73390500" Language="SFX">
							<ShortName>PulseInstruments\PL_Drone_01_Index_18\nms2017_mids_21.wav</ShortName>
							<Path>SFX\PulseInstruments\PL_Drone_01_Index_18\nms2017_mids_21_358B4EC2.wem</Path>
						</File>
						<File Id="78405684" Language="SFX">
							<ShortName>PulseInstruments\PL_Drone_01_Index_18\nms2017_mids_24.wav</ShortName>
							<Path>SFX\PulseInstruments\PL_Drone_01_Index_18\nms2017_mids_24_358B4EC2.wem</Path>
						</File>
						<File Id="104146044" Language="SFX">
							<ShortName>PulseInstruments\PL_Drone_01_Index_18\nms2017_mids_32.wav</ShortName>
							<Path>SFX\PulseInstruments\PL_Drone_01_Index_18\nms2017_mids_32_358B4EC2.wem</Path>
						</File>
						<File Id="139403601" Language="SFX">
							<ShortName>PulseInstruments\PL_Drone_01_Index_18\nms2017_mids_48.wav</ShortName>
							<Path>SFX\PulseInstruments\PL_Drone_01_Index_18\nms2017_mids_48_358B4EC2.wem</Path>
						</File>
						<File Id="145072364" Language="SFX">
							<ShortName>PulseInstruments\PL_Drone_01_Index_18\nms2017_mids_46.wav</ShortName>
							<Path>SFX\PulseInstruments\PL_Drone_01_Index_18\nms2017_mids_46_358B4EC2.wem</Path>
						</File>
						<File Id="151560825" Language="SFX">
							<ShortName>PulseInstruments\PL_Drone_01_Index_18\nms2017_mids_36.wav</ShortName>
							<Path>SFX\PulseInstruments\PL_Drone_01_Index_18\nms2017_mids_36_358B4EC2.wem</Path>
						</File>
						<File Id="159059374" Language="SFX">
							<ShortName>PulseInstruments\PL_Drone_01_Index_18\nms2017_mids_30.wav</ShortName>
							<Path>SFX\PulseInstruments\PL_Drone_01_Index_18\nms2017_mids_30_358B4EC2.wem</Path>
						</File>
						<File Id="160551958" Language="SFX">
							<ShortName>PulseInstruments\PL_Drone_01_Index_18\nms2017_mids_49.wav</ShortName>
							<Path>SFX\PulseInstruments\PL_Drone_01_Index_18\nms2017_mids_49_358B4EC2.wem</Path>
						</File>
						<File Id="171495126" Language="SFX">
							<ShortName>PulseInstruments\PL_Drone_01_Index_18\nms2017_mids_2.wav</ShortName>
							<Path>SFX\PulseInstruments\PL_Drone_01_Index_18\nms2017_mids_2_358B4EC2.wem</Path>
						</File>
						<File Id="181873139" Language="SFX">
							<ShortName>PulseInstruments\PL_Drone_01_Index_18\nms2017_mids_7.wav</ShortName>
							<Path>SFX\PulseInstruments\PL_Drone_01_Index_18\nms2017_mids_7_358B4EC2.wem</Path>
						</File>
						<File Id="185404200" Language="SFX">
							<ShortName>PulseInstruments\PL_Drone_01_Index_18\nms2017_mids_31.wav</ShortName>
							<Path>SFX\PulseInstruments\PL_Drone_01_Index_18\nms2017_mids_31_358B4EC2.wem</Path>
						</File>
						<File Id="201137157" Language="SFX">
							<ShortName>PulseInstruments\PL_Drone_01_Index_18\nms2017_mids_20.wav</ShortName>
							<Path>SFX\PulseInstruments\PL_Drone_01_Index_18\nms2017_mids_20_358B4EC2.wem</Path>
						</File>
						<File Id="243498899" Language="SFX">
							<ShortName>PulseInstruments\PL_Drone_01_Index_18\nms2017_mids_29.wav</ShortName>
							<Path>SFX\PulseInstruments\PL_Drone_01_Index_18\nms2017_mids_29_358B4EC2.wem</Path>
						</File>
						<File Id="246024998" Language="SFX">
							<ShortName>PulseInstruments\PL_Drone_01_Index_18\nms2017_mids_28.wav</ShortName>
							<Path>SFX\PulseInstruments\PL_Drone_01_Index_18\nms2017_mids_28_358B4EC2.wem</Path>
						</File>
						<File Id="258506651" Language="SFX">
							<ShortName>PulseInstruments\PL_Drone_01_Index_18\nms2017_mids_18.wav</ShortName>
							<Path>SFX\PulseInstruments\PL_Drone_01_Index_18\nms2017_mids_18_358B4EC2.wem</Path>
						</File>
						<File Id="267998379" Language="SFX">
							<ShortName>PulseInstruments\PL_Drone_01_Index_18\nms2017_mids_8.wav</ShortName>
							<Path>SFX\PulseInstruments\PL_Drone_01_Index_18\nms2017_mids_8_358B4EC2.wem</Path>
						</File>
						<File Id="293727151" Language="SFX">
							<ShortName>PulseInstruments\PL_Drone_01_Index_18\nms2017_mids_41.wav</ShortName>
							<Path>SFX\PulseInstruments\PL_Drone_01_Index_18\nms2017_mids_41_358B4EC2.wem</Path>
						</File>
						<File Id="293962685" Language="SFX">
							<ShortName>PulseInstruments\PL_Drone_01_Index_18\nms2017_mids_42.wav</ShortName>
							<Path>SFX\PulseInstruments\PL_Drone_01_Index_18\nms2017_mids_42_358B4EC2.wem</Path>
						</File>
						<File Id="327894570" Language="SFX">
							<ShortName>PulseInstruments\PL_Drone_01_Index_18\nms2017_mids_44.wav</ShortName>
							<Path>SFX\PulseInstruments\PL_Drone_01_Index_18\nms2017_mids_44_358B4EC2.wem</Path>
						</File>
						<File Id="349017833" Language="SFX">
							<ShortName>PulseInstruments\PL_Drone_01_Index_18\nms2017_mids_5.wav</ShortName>
							<Path>SFX\PulseInstruments\PL_Drone_01_Index_18\nms2017_mids_5_358B4EC2.wem</Path>
						</File>
						<File Id="354590471" Language="SFX">
							<ShortName>PulseInstruments\PL_Drone_01_Index_18\nms2017_mids_47.wav</ShortName>
							<Path>SFX\PulseInstruments\PL_Drone_01_Index_18\nms2017_mids_47_358B4EC2.wem</Path>
						</File>
						<File Id="391598185" Language="SFX">
							<ShortName>PulseInstruments\PL_Drone_01_Index_18\nms2017_mids_16.wav</ShortName>
							<Path>SFX\PulseInstruments\PL_Drone_01_Index_18\nms2017_mids_16_358B4EC2.wem</Path>
						</File>
						<File Id="428779561" Language="SFX">
							<ShortName>PulseInstruments\PL_Drone_01_Index_18\nms2017_mids_17.wav</ShortName>
							<Path>SFX\PulseInstruments\PL_Drone_01_Index_18\nms2017_mids_17_358B4EC2.wem</Path>
						</File>
						<File Id="484789896" Language="SFX">
							<ShortName>PulseInstruments\PL_Drone_01_Index_18\nms2017_mids_19.wav</ShortName>
							<Path>SFX\PulseInstruments\PL_Drone_01_Index_18\nms2017_mids_19_358B4EC2.wem</Path>
						</File>
						<File Id="496291973" Language="SFX">
							<ShortName>PulseInstruments\PL_Drone_01_Index_18\nms2017_mids_15.wav</ShortName>
							<Path>SFX\PulseInstruments\PL_Drone_01_Index_18\nms2017_mids_15_358B4EC2.wem</Path>
						</File>
						<File Id="533565181" Language="SFX">
							<ShortName>PulseInstruments\PL_Drone_01_Index_18\nms2017_mids_1.wav</ShortName>
							<Path>SFX\PulseInstruments\PL_Drone_01_Index_18\nms2017_mids_1_358B4EC2.wem</Path>
						</File>
						<File Id="538431834" Language="SFX">
							<ShortName>PulseInstruments\PL_Drone_01_Index_18\nms2017_mids_4.wav</ShortName>
							<Path>SFX\PulseInstruments\PL_Drone_01_Index_18\nms2017_mids_4_358B4EC2.wem</Path>
						</File>
						<File Id="551898508" Language="SFX">
							<ShortName>PulseInstruments\PL_Drone_01_Index_18\nms2017_mids_39.wav</ShortName>
							<Path>SFX\PulseInstruments\PL_Drone_01_Index_18\nms2017_mids_39_358B4EC2.wem</Path>
						</File>
						<File Id="578643919" Language="SFX">
							<ShortName>PulseInstruments\PL_Drone_01_Index_18\nms2017_mids_22.wav</ShortName>
							<Path>SFX\PulseInstruments\PL_Drone_01_Index_18\nms2017_mids_22_358B4EC2.wem</Path>
						</File>
						<File Id="595598722" Language="SFX">
							<ShortName>PulseInstruments\PL_Drone_01_Index_18\nms2017_mids_40.wav</ShortName>
							<Path>SFX\PulseInstruments\PL_Drone_01_Index_18\nms2017_mids_40_358B4EC2.wem</Path>
						</File>
						<File Id="609330193" Language="SFX">
							<ShortName>PulseInstruments\PL_Drone_01_Index_18\nms2017_mids_35.wav</ShortName>
							<Path>SFX\PulseInstruments\PL_Drone_01_Index_18\nms2017_mids_35_358B4EC2.wem</Path>
						</File>
						<File Id="666768199" Language="SFX">
							<ShortName>PulseInstruments\PL_Drone_01_Index_18\nms2017_mids_3.wav</ShortName>
							<Path>SFX\PulseInstruments\PL_Drone_01_Index_18\nms2017_mids_3_358B4EC2.wem</Path>
						</File>
						<File Id="715752092" Language="SFX">
							<ShortName>PulseInstruments\PL_Drone_01_Index_18\nms2017_mids_11.wav</ShortName>
							<Path>SFX\PulseInstruments\PL_Drone_01_Index_18\nms2017_mids_11_358B4EC2.wem</Path>
						</File>
						<File Id="724120139" Language="SFX">
							<ShortName>PulseInstruments\PL_Drone_01_Index_18\nms2017_mids_23.wav</ShortName>
							<Path>SFX\PulseInstruments\PL_Drone_01_Index_18\nms2017_mids_23_358B4EC2.wem</Path>
						</File>
						<File Id="725260388" Language="SFX">
							<ShortName>PulseInstruments\PL_Drone_01_Index_18\nms2017_mids_26.wav</ShortName>
							<Path>SFX\PulseInstruments\PL_Drone_01_Index_18\nms2017_mids_26_358B4EC2.wem</Path>
						</File>
						<File Id="761747467" Language="SFX">
							<ShortName>PulseInstruments\PL_Drone_01_Index_18\nms2017_mids_37.wav</ShortName>
							<Path>SFX\PulseInstruments\PL_Drone_01_Index_18\nms2017_mids_37_358B4EC2.wem</Path>
						</File>
						<File Id="772435528" Language="SFX">
							<ShortName>PulseInstruments\PL_Drone_01_Index_18\nms2017_mids_25.wav</ShortName>
							<Path>SFX\PulseInstruments\PL_Drone_01_Index_18\nms2017_mids_25_358B4EC2.wem</Path>
						</File>
						<File Id="821033019" Language="SFX">
							<ShortName>PulseInstruments\PL_Drone_01_Index_18\nms2017_mids_52.wav</ShortName>
							<Path>SFX\PulseInstruments\PL_Drone_01_Index_18\nms2017_mids_52_358B4EC2.wem</Path>
						</File>
						<File Id="872219304" Language="SFX">
							<ShortName>PulseInstruments\PL_Drone_01_Index_18\nms2017_mids_9.wav</ShortName>
							<Path>SFX\PulseInstruments\PL_Drone_01_Index_18\nms2017_mids_9_358B4EC2.wem</Path>
						</File>
						<File Id="882825897" Language="SFX">
							<ShortName>PulseInstruments\PL_Drone_01_Index_18\nms2017_mids_13.wav</ShortName>
							<Path>SFX\PulseInstruments\PL_Drone_01_Index_18\nms2017_mids_13_358B4EC2.wem</Path>
						</File>
						<File Id="936709843" Language="SFX">
							<ShortName>PulseInstruments\PL_Drone_01_Index_18\nms2017_mids_6.wav</ShortName>
							<Path>SFX\PulseInstruments\PL_Drone_01_Index_18\nms2017_mids_6_358B4EC2.wem</Path>
						</File>
						<File Id="963602345" Language="SFX">
							<ShortName>PulseInstruments\PL_Drone_01_Index_18\nms2017_mids_45.wav</ShortName>
							<Path>SFX\PulseInstruments\PL_Drone_01_Index_18\nms2017_mids_45_358B4EC2.wem</Path>
						</File>
						<File Id="966831671" Language="SFX">
							<ShortName>PulseInstruments\PL_Drone_01_Index_18\nms2017_mids_10.wav</ShortName>
							<Path>SFX\PulseInstruments\PL_Drone_01_Index_18\nms2017_mids_10_358B4EC2.wem</Path>
						</File>
						<File Id="991555369" Language="SFX">
							<ShortName>PulseInstruments\PL_Drone_01_Index_18\nms2017_mids_12.wav</ShortName>
							<Path>SFX\PulseInstruments\PL_Drone_01_Index_18\nms2017_mids_12_358B4EC2.wem</Path>
						</File>
						<File Id="999061691" Language="SFX">
							<ShortName>PulseInstruments\PL_Drone_01_Index_18\nms2017_mids_14.wav</ShortName>
							<Path>SFX\PulseInstruments\PL_Drone_01_Index_18\nms2017_mids_14_358B4EC2.wem</Path>
						</File>
						<File Id="1008417992" Language="SFX">
							<ShortName>PulseInstruments\PL_Drone_01_Index_18\nms2017_mids_34.wav</ShortName>
							<Path>SFX\PulseInstruments\PL_Drone_01_Index_18\nms2017_mids_34_358B4EC2.wem</Path>
						</File>
						<File Id="1057844119" Language="SFX">
							<ShortName>PulseInstruments\PL_Drone_01_Index_18\nms2017_mids_38.wav</ShortName>
							<Path>SFX\PulseInstruments\PL_Drone_01_Index_18\nms2017_mids_38_358B4EC2.wem</Path>
						</File>
						<File Id="1058731023" Language="SFX">
							<ShortName>PulseInstruments\PL_Drone_01_Index_18\nms2017_mids_33.wav</ShortName>
							<Path>SFX\PulseInstruments\PL_Drone_01_Index_18\nms2017_mids_33_358B4EC2.wem</Path>
						</File>
					</ReferencedStreamedFiles>
				</Event>
			</IncludedEvents>
			<GameParameters>
				<GameParameter Id="18151427" Name="Pulse_Event_PanLR" ObjectPath="\Game Parameters\Default Work Unit\Pulse\Pulse_Event_PanLR"/>
				<GameParameter Id="1891889666" Name="Pulse_Event_Pitch" ObjectPath="\Game Parameters\Default Work Unit\Pulse\Pulse_Event_Pitch"/>
				<GameParameter Id="2954454836" Name="Pulse_Event_SendBus_03" ObjectPath="\Game Parameters\Default Work Unit\Pulse\Pulse_Event_SendBus_03"/>
				<GameParameter Id="2954454837" Name="Pulse_Event_SendBus_02" ObjectPath="\Game Parameters\Default Work Unit\Pulse\Pulse_Event_SendBus_02"/>
				<GameParameter Id="2954454838" Name="Pulse_Event_SendBus_01" ObjectPath="\Game Parameters\Default Work Unit\Pulse\Pulse_Event_SendBus_01"/>
				<GameParameter Id="2954454839" Name="Pulse_Event_SendBus_00" ObjectPath="\Game Parameters\Default Work Unit\Pulse\Pulse_Event_SendBus_00"/>
				<GameParameter Id="3465058902" Name="Pulse_Event_Volume" ObjectPath="\Game Parameters\Default Work Unit\Pulse\Pulse_Event_Volume"/>
				<GameParameter Id="4145342657" Name="Pulse_Event_PanFR" ObjectPath="\Game Parameters\Default Work Unit\Pulse\Pulse_Event_PanFR"/>
			</GameParameters>
		</SoundBank>
	</SoundBanks>
</SoundBanksInfo>
