<?xml version="1.0" encoding="utf-8"?>
<SoundBanksInfo Platform="Windows" BasePlatform="Windows" SchemaVersion="12" SoundbankVersion="135">
	<RootPaths>
		<ProjectRoot>T:\BUILDAGENT\WORK\9A7A8DD8B2E0B6C8\GAME\ASSETS\EXPORTED\AUDIO\</ProjectRoot>
		<SourceFilesRoot>T:\BUILDAGENT\WORK\9A7A8DD8B2E0B6C8\GAME\ASSETS\EXPORTED\AUDIO\.cache\Windows\</SourceFilesRoot>
		<SoundBanksRoot>T:\BUILDAGENT\WORK\9A7A8DD8B2E0B6C8\GAME\ASSETS\GAMEDATA\Audio\Windows\</SoundBanksRoot>
		<ExternalSourcesInputFile></ExternalSourcesInputFile>
		<ExternalSourcesOutputRoot>T:\BUILDAGENT\WORK\9A7A8DD8B2E0B6C8\GAME\ASSETS\EXPORTED\AUDIO\GeneratedSoundBanks\Windows</ExternalSourcesOutputRoot>
	</RootPaths>
	<SoundBanks>
		<SoundBank Id="3652157304" Language="SFX">
			<ObjectPath>\SoundBanks\PulseInstruments\PulseInstrument_PL_Melody_HI_Index_10</ObjectPath>
			<ShortName>PulseInstrument_PL_Melody_HI_Index_10</ShortName>
			<Path>PulseInstrument_PL_Melody_HI_Index_10.bnk</Path>
			<IncludedEvents>
				<Event Id="3025157699" Name="Play_PL_Melody_HI_Index_10_tetsuo_planetHi_1" ObjectPath="\Events\PulseInstruments\PulseInstrument_PL_Melody_HI_Index_10\Play_PL_Melody_HI_Index_10_tetsuo_planetHi_1">
					<ReferencedStreamedFiles>
						<File Id="31751406" Language="SFX">
							<ShortName>PulseInstruments\PL_Melody_HI_Index_10\tetsuo_planetHi_7.wav</ShortName>
							<Path>SFX\PulseInstruments\PL_Melody_HI_Index_10\tetsuo_planetHi_7_358B4EC2.wem</Path>
						</File>
						<File Id="36860283" Language="SFX">
							<ShortName>PulseInstruments\PL_Melody_HI_Index_10\tetsuo_planetHi_11.wav</ShortName>
							<Path>SFX\PulseInstruments\PL_Melody_HI_Index_10\tetsuo_planetHi_11_358B4EC2.wem</Path>
						</File>
						<File Id="75928694" Language="SFX">
							<ShortName>PulseInstruments\PL_Melody_HI_Index_10\tetsuo_planetHi_16.wav</ShortName>
							<Path>SFX\PulseInstruments\PL_Melody_HI_Index_10\tetsuo_planetHi_16_358B4EC2.wem</Path>
						</File>
						<File Id="130093396" Language="SFX">
							<ShortName>PulseInstruments\PL_Melody_HI_Index_10\tetsuo_planetHi_8.wav</ShortName>
							<Path>SFX\PulseInstruments\PL_Melody_HI_Index_10\tetsuo_planetHi_8_358B4EC2.wem</Path>
						</File>
						<File Id="165636568" Language="SFX">
							<ShortName>PulseInstruments\PL_Melody_HI_Index_10\tetsuo_planetHi_5.wav</ShortName>
							<Path>SFX\PulseInstruments\PL_Melody_HI_Index_10\tetsuo_planetHi_5_358B4EC2.wem</Path>
						</File>
						<File Id="376680334" Language="SFX">
							<ShortName>PulseInstruments\PL_Melody_HI_Index_10\tetsuo_planetHi_12.wav</ShortName>
							<Path>SFX\PulseInstruments\PL_Melody_HI_Index_10\tetsuo_planetHi_12_358B4EC2.wem</Path>
						</File>
						<File Id="523019615" Language="SFX">
							<ShortName>PulseInstruments\PL_Melody_HI_Index_10\tetsuo_planetHi_3.wav</ShortName>
							<Path>SFX\PulseInstruments\PL_Melody_HI_Index_10\tetsuo_planetHi_3_358B4EC2.wem</Path>
						</File>
						<File Id="526314883" Language="SFX">
							<ShortName>PulseInstruments\PL_Melody_HI_Index_10\tetsuo_planetHi_9.wav</ShortName>
							<Path>SFX\PulseInstruments\PL_Melody_HI_Index_10\tetsuo_planetHi_9_358B4EC2.wem</Path>
						</File>
						<File Id="581644587" Language="SFX">
							<ShortName>PulseInstruments\PL_Melody_HI_Index_10\tetsuo_planetHi_14.wav</ShortName>
							<Path>SFX\PulseInstruments\PL_Melody_HI_Index_10\tetsuo_planetHi_14_358B4EC2.wem</Path>
						</File>
						<File Id="603792573" Language="SFX">
							<ShortName>PulseInstruments\PL_Melody_HI_Index_10\tetsuo_planetHi_4.wav</ShortName>
							<Path>SFX\PulseInstruments\PL_Melody_HI_Index_10\tetsuo_planetHi_4_358B4EC2.wem</Path>
						</File>
						<File Id="616894729" Language="SFX">
							<ShortName>PulseInstruments\PL_Melody_HI_Index_10\tetsuo_planetHi_15.wav</ShortName>
							<Path>SFX\PulseInstruments\PL_Melody_HI_Index_10\tetsuo_planetHi_15_358B4EC2.wem</Path>
						</File>
						<File Id="646092241" Language="SFX">
							<ShortName>PulseInstruments\PL_Melody_HI_Index_10\tetsuo_planetHi_10.wav</ShortName>
							<Path>SFX\PulseInstruments\PL_Melody_HI_Index_10\tetsuo_planetHi_10_358B4EC2.wem</Path>
						</File>
						<File Id="681869341" Language="SFX">
							<ShortName>PulseInstruments\PL_Melody_HI_Index_10\tetsuo_planetHi_13.wav</ShortName>
							<Path>SFX\PulseInstruments\PL_Melody_HI_Index_10\tetsuo_planetHi_13_358B4EC2.wem</Path>
						</File>
						<File Id="723564211" Language="SFX">
							<ShortName>PulseInstruments\PL_Melody_HI_Index_10\tetsuo_planetHi_2.wav</ShortName>
							<Path>SFX\PulseInstruments\PL_Melody_HI_Index_10\tetsuo_planetHi_2_358B4EC2.wem</Path>
						</File>
						<File Id="791426929" Language="SFX">
							<ShortName>PulseInstruments\PL_Melody_HI_Index_10\tetsuo_planetHi_6.wav</ShortName>
							<Path>SFX\PulseInstruments\PL_Melody_HI_Index_10\tetsuo_planetHi_6_358B4EC2.wem</Path>
						</File>
						<File Id="961860847" Language="SFX">
							<ShortName>PulseInstruments\PL_Melody_HI_Index_10\tetsuo_planetHi_1.wav</ShortName>
							<Path>SFX\PulseInstruments\PL_Melody_HI_Index_10\tetsuo_planetHi_1_358B4EC2.wem</Path>
						</File>
					</ReferencedStreamedFiles>
				</Event>
			</IncludedEvents>
			<GameParameters>
				<GameParameter Id="18151427" Name="Pulse_Event_PanLR" ObjectPath="\Game Parameters\Default Work Unit\Pulse\Pulse_Event_PanLR"/>
				<GameParameter Id="1891889666" Name="Pulse_Event_Pitch" ObjectPath="\Game Parameters\Default Work Unit\Pulse\Pulse_Event_Pitch"/>
				<GameParameter Id="2954454836" Name="Pulse_Event_SendBus_03" ObjectPath="\Game Parameters\Default Work Unit\Pulse\Pulse_Event_SendBus_03"/>
				<GameParameter Id="2954454837" Name="Pulse_Event_SendBus_02" ObjectPath="\Game Parameters\Default Work Unit\Pulse\Pulse_Event_SendBus_02"/>
				<GameParameter Id="2954454838" Name="Pulse_Event_SendBus_01" ObjectPath="\Game Parameters\Default Work Unit\Pulse\Pulse_Event_SendBus_01"/>
				<GameParameter Id="2954454839" Name="Pulse_Event_SendBus_00" ObjectPath="\Game Parameters\Default Work Unit\Pulse\Pulse_Event_SendBus_00"/>
				<GameParameter Id="3465058902" Name="Pulse_Event_Volume" ObjectPath="\Game Parameters\Default Work Unit\Pulse\Pulse_Event_Volume"/>
				<GameParameter Id="4145342657" Name="Pulse_Event_PanFR" ObjectPath="\Game Parameters\Default Work Unit\Pulse\Pulse_Event_PanFR"/>
			</GameParameters>
		</SoundBank>
	</SoundBanks>
</SoundBanksInfo>
