<?xml version="1.0" encoding="utf-8"?>
<SoundBanksInfo Platform="Windows" BasePlatform="Windows" SchemaVersion="12" SoundbankVersion="135">
	<RootPaths>
		<ProjectRoot>T:\BUILDAGENT\WORK\9A7A8DD8B2E0B6C8\GAME\ASSETS\EXPORTED\AUDIO\</ProjectRoot>
		<SourceFilesRoot>T:\BUILDAGENT\WORK\9A7A8DD8B2E0B6C8\GAME\ASSETS\EXPORTED\AUDIO\.cache\Windows\</SourceFilesRoot>
		<SoundBanksRoot>T:\BUILDAGENT\WORK\9A7A8DD8B2E0B6C8\GAME\ASSETS\GAMEDATA\Audio\Windows\</SoundBanksRoot>
		<ExternalSourcesInputFile></ExternalSourcesInputFile>
		<ExternalSourcesOutputRoot>T:\BUILDAGENT\WORK\9A7A8DD8B2E0B6C8\GAME\ASSETS\EXPORTED\AUDIO\GeneratedSoundBanks\Windows</ExternalSourcesOutputRoot>
	</RootPaths>
	<SoundBanks>
		<SoundBank Id="3584219824" Language="SFX">
			<ObjectPath>\SoundBanks\PulseInstruments\PulseInstrument_SP_Synth_Index_13</ObjectPath>
			<ShortName>PulseInstrument_SP_Synth_Index_13</ShortName>
			<Path>PulseInstrument_SP_Synth_Index_13.bnk</Path>
			<IncludedEvents>
				<Event Id="496248595" Name="Play_SP_Synth_Index_13_beyond_slowSynth_6" ObjectPath="\Events\PulseInstruments\PulseInstrument_SP_Synth_Index_13\Play_SP_Synth_Index_13_beyond_slowSynth_6">
					<ReferencedStreamedFiles>
						<File Id="74759676" Language="SFX">
							<ShortName>PulseInstruments\SP_Synth_Index_13\beyond_slowSynth_7.wav</ShortName>
							<Path>SFX\PulseInstruments\SP_Synth_Index_13\beyond_slowSynth_7_358B4EC2.wem</Path>
						</File>
						<File Id="202640769" Language="SFX">
							<ShortName>PulseInstruments\SP_Synth_Index_13\beyond_slowSynth_6.wav</ShortName>
							<Path>SFX\PulseInstruments\SP_Synth_Index_13\beyond_slowSynth_6_358B4EC2.wem</Path>
						</File>
						<File Id="451257654" Language="SFX">
							<ShortName>PulseInstruments\SP_Synth_Index_13\beyond_slowSynth_3.wav</ShortName>
							<Path>SFX\PulseInstruments\SP_Synth_Index_13\beyond_slowSynth_3_358B4EC2.wem</Path>
						</File>
						<File Id="593244589" Language="SFX">
							<ShortName>PulseInstruments\SP_Synth_Index_13\beyond_slowSynth_8.wav</ShortName>
							<Path>SFX\PulseInstruments\SP_Synth_Index_13\beyond_slowSynth_8_358B4EC2.wem</Path>
						</File>
						<File Id="798170554" Language="SFX">
							<ShortName>PulseInstruments\SP_Synth_Index_13\beyond_slowSynth_2.wav</ShortName>
							<Path>SFX\PulseInstruments\SP_Synth_Index_13\beyond_slowSynth_2_358B4EC2.wem</Path>
						</File>
						<File Id="818084363" Language="SFX">
							<ShortName>PulseInstruments\SP_Synth_Index_13\beyond_slowSynth_5.wav</ShortName>
							<Path>SFX\PulseInstruments\SP_Synth_Index_13\beyond_slowSynth_5_358B4EC2.wem</Path>
						</File>
						<File Id="841882229" Language="SFX">
							<ShortName>PulseInstruments\SP_Synth_Index_13\beyond_slowSynth_4.wav</ShortName>
							<Path>SFX\PulseInstruments\SP_Synth_Index_13\beyond_slowSynth_4_358B4EC2.wem</Path>
						</File>
						<File Id="1039326082" Language="SFX">
							<ShortName>PulseInstruments\SP_Synth_Index_13\beyond_slowSynth_1.wav</ShortName>
							<Path>SFX\PulseInstruments\SP_Synth_Index_13\beyond_slowSynth_1_358B4EC2.wem</Path>
						</File>
					</ReferencedStreamedFiles>
				</Event>
			</IncludedEvents>
			<GameParameters>
				<GameParameter Id="18151427" Name="Pulse_Event_PanLR" ObjectPath="\Game Parameters\Default Work Unit\Pulse\Pulse_Event_PanLR"/>
				<GameParameter Id="1891889666" Name="Pulse_Event_Pitch" ObjectPath="\Game Parameters\Default Work Unit\Pulse\Pulse_Event_Pitch"/>
				<GameParameter Id="2954454836" Name="Pulse_Event_SendBus_03" ObjectPath="\Game Parameters\Default Work Unit\Pulse\Pulse_Event_SendBus_03"/>
				<GameParameter Id="2954454837" Name="Pulse_Event_SendBus_02" ObjectPath="\Game Parameters\Default Work Unit\Pulse\Pulse_Event_SendBus_02"/>
				<GameParameter Id="2954454838" Name="Pulse_Event_SendBus_01" ObjectPath="\Game Parameters\Default Work Unit\Pulse\Pulse_Event_SendBus_01"/>
				<GameParameter Id="2954454839" Name="Pulse_Event_SendBus_00" ObjectPath="\Game Parameters\Default Work Unit\Pulse\Pulse_Event_SendBus_00"/>
				<GameParameter Id="3465058902" Name="Pulse_Event_Volume" ObjectPath="\Game Parameters\Default Work Unit\Pulse\Pulse_Event_Volume"/>
				<GameParameter Id="4145342657" Name="Pulse_Event_PanFR" ObjectPath="\Game Parameters\Default Work Unit\Pulse\Pulse_Event_PanFR"/>
			</GameParameters>
		</SoundBank>
	</SoundBanks>
</SoundBanksInfo>
